<?xml version="1.0" encoding="UTF-8"?>
<rdf:RDF xmlns:rdf="http://www.w3.org/1999/02/22-rdf-syntax-ns#"
         xmlns:dc="http://purl.org/dc/elements/1.1/">
   <rdf:Description>
      <dc:title>Woordenboek der Grieksche en Romeinsche Oudheid</dc:title>
      <dc:creator>Johannes George Schlimmer (1833–1901)</dc:creator>
      <dc:creator>Zacharias Cohen de Boer (1847–1915)</dc:creator>
      <dc:creator>C. G. Th. W. Koch</dc:creator>
      <dc:publisher>Project Gutenberg, Urbana, Illinois, USA., 2011-01-15</dc:publisher>
      <dc:date>2011-01-15</dc:date>
      <dc:rights>Dit eBoek is voor kosteloos gebruik door iedereen overal, met vrijwel geen beperkingen van welke soort dan ook. U mag het kopiëren, weggeven of hergebruiken onder de voorwaarden van de Project Gutenberg Licentie bij dit eBoek of on-line op www.gutenberg.org.

 Dit eBoek is geproduceerd door het on-line gedistribueerd correctieteam op www.pgdp.net.

 </dc:rights>
      <dc:description>Een encyclopedisch woordenboek over de klassieke oudheid.</dc:description>
      <dc:identifier>pg:34955</dc:identifier>
   </rdf:Description>
</rdf:RDF>